<PAMDataset>
  <PAMRasterBand band="1">
    <Description>topo_broc</Description>
    <Histograms>
      <HistItem>
        <HistMin>671.5406840820313</HistMin>
        <HistMax>681.9798237304688</HistMax>
        <BucketCount>1000</BucketCount>
        <IncludeOutOfRange>0</IncludeOutOfRange>
        <Approximate>0</Approximate>
        <HistCounts>1|0|0|0|0|1|1|0|2|0|0|0|2|2|1|4|1|1|1|0|97|7|5|6|8|10|6|8|12|12|4|11|6|9|7|9|4|13|12|4|10|26|723|478|405|42|37|25|34|34|34|29|26|29|36|30|28|36|34|30|33|38|35|56|49|56|134|97|135|53|37|46|62|35|60|50|42|49|49|54|42|48|49|35|53|61|57|126|123|150|154|92|26|41|28|34|37|26|36|23|34|32|32|18|33|20|22|31|33|35|33|24|30|52|40|85|41|35|36|33|45|38|42|40|44|45|25|46|32|38|47|49|48|48|48|51|38|65|75|675|326|50|43|39|42|56|28|47|31|33|39|32|36|31|31|27|37|21|26|39|23|26|27|101|26|32|27|26|26|34|26|29|24|19|23|33|26|19|20|24|19|26|22|32|29|33|52|46|69|27|35|27|19|28|31|16|25|40|17|31|34|15|30|34|27|26|33|31|38|19|40|115|194|69|54|60|59|44|53|46|50|58|43|61|46|46|64|48|54|62|46|56|63|56|74|361|240|106|85|94|79|94|94|66|82|89|95|66|70|103|89|74|88|89|90|99|91|119|503|659|194|159|149|148|131|147|121|125|120|123|111|97|95|101|98|102|84|83|102|85|117|96|119|394|460|163|120|100|107|81|92|92|77|79|79|83|79|96|78|64|95|70|86|86|93|105|182|292|240|229|215|143|120|149|128|158|131|140|163|173|160|179|175|194|252|238|251|246|243|273|312|724|509|319|272|226|210|167|182|151|164|153|169|165|165|151|158|154|164|160|172|170|181|214|220|548|707|297|217|186|197|171|178|170|172|177|168|150|153|156|177|144|135|178|137|173|153|159|527|454|428|158|136|153|143|144|131|139|137|147|133|153|139|126|127|147|125|145|130|137|129|174|362|566|324|161|147|144|139|136|129|140|121|116|117|117|111|115|100|117|106|122|123|120|134|136|391|483|238|168|110|123|101|90|87|96|84|80|81|64|73|61|63|64|69|82|58|75|62|69|62|348|86|59|53|61|51|57|52|46|50|37|62|42|51|51|66|58|57|56|49|43|44|64|227|120|215|75|58|62|55|72|62|70|51|55|55|68|48|39|47|53|37|34|37|46|47|27|54|150|52|42|40|34|37|42|33|36|41|28|40|39|39|30|31|47|24|40|36|49|46|45|87|166|58|36|45|46|38|30|33|34|32|31|36|37|39|34|31|29|22|35|29|39|24|57|156|74|62|63|63|30|37|43|46|29|46|41|42|44|40|40|55|50|56|52|68|97|185|103|90|45|46|42|30|40|41|35|38|39|29|43|34|30|29|34|28|37|32|36|26|31|28|27|51|209|35|43|47|29|40|26|30|24|31|30|26|33|23|31|23|30|34|24|24|29|17|36|54|198|36|39|31|29|27|36|24|24|24|31|25|33|36|33|29|18|28|33|27|30|28|33|61|28|29|28|24|20|24|31|36|21|28|29|27|27|31|29|19|21|23|25|30|27|27|33|27|29|21|24|23|20|19|26|16|27|20|17|19|14|22|20|23|16|23|22|23|33|23|22|21|20|19|21|26|23|25|16|19|15|24|21|16|17|20|23|30|27|22|23|23|33|22|23|24|28|26|26|32|30|26|22|24|31|43|31|37|35|33|43|31|43|33|37|30|30|26|23|19|15|16|19|20|15|20|20|15|18|18|21|27|19|10|16|14|16|18|14|20|13|16|21|22|21|16|17|20|22|15|20|21|18|18|14|16|18|14|18|15|17|20|21|20|20|18|19|21|16|19|18|15|18|19|19|16|12|22|15|15|15|20|19|23|20|18|24|18|17|23|16|23|31|29|30|31|30|34|25|29|36|28|27|32|28|34|36|32|31|30|28|28|25|27|33|26|32|27|24|29|29|29|25|27|30|28|28|29|24|21|29|30|29|22|26|26|26|24|27|21|20|27|24|27|31|30|24|30|22|22|25|24|22|22|18|23|26|27|26|23|24|24|20|22|25|26|19|18|27|22|23|24|23|22|24|22|20|23|19|23|26|22|28|28|29|27|92|1157|69|49|57|44|54|44|55|50|44|51|37|44|46|46|39|40|44|34|49|31|41|28|38|40|30|37|22|26|24|25|20|28|28|16|27|16|27|23|20|19|18|24|17|22|16|18|17|20|19|15|18|12|18|12|17|13|12|16|12|15|13|14|17|15|20|12|15|12|16|10|16|13|15|13|14|12|12|15|10|14|13|11|12|14|10|9|9|7|7|5|4|3|2</HistCounts>
      </HistItem>
    </Histograms>
    <Metadata>
      <MDI key="LAYER_TYPE">athematic</MDI>
      <MDI key="STATISTICS_MAXIMUM">681.974609375</MDI>
      <MDI key="STATISTICS_MEAN">675.76784044026</MDI>
      <MDI key="STATISTICS_MINIMUM">671.5458984375</MDI>
      <MDI key="STATISTICS_STDDEV">2.2982558899166</MDI>
    </Metadata>
  </PAMRasterBand>
</PAMDataset>
